tesserarius/__init__.py
tesserarius/main.py
tesserarius/roles.py
tesserarius/serviceaccount.py
tesserarius/tasks.py
tesserarius/utils.py
tesserarius/extensions/__init__.py
tesserarius/extensions/roles.py
tesserarius/extensions/serviceaccount.py
tesserarius/extensions/tasks.py
tesserarius/platform/__init__.py
tesserarius/platform/roles.py
tesserarius/platform/serviceaccount.py
tesserarius/platform/tasks.py
tesserarius-0.0.5.dist-info/METADATA
tesserarius-0.0.5.dist-info/RECORD
tesserarius-0.0.5.dist-info/WHEEL
tesserarius-0.0.5.dist-info/entry_points.txt
tesserarius-0.0.5.dist-info/top_level.txt
tesserarius-0.0.5.dist-info/zip-safe
