Metadata-Version: 2.1
Name: tesserarius
Version: 0.0.5
Summary: CLI application that make it easier to perform DevOps on Kubernetes and GCloud 
Home-page: https://github.com/rehive/tesserarius/
Author: Rehive
Author-email: info@rehive.com
License: MIT License
Keywords: gcloud docker python helm kubernetes build automation deploy
Platform: UNKNOWN
Classifier: Development Status :: 4 - Beta
Classifier: Intended Audience :: System Administrators
Classifier: Topic :: Software Development :: Build Tools
Classifier: Topic :: System :: Installation/Setup
Classifier: Topic :: System :: Software Distribution
Classifier: Operating System :: OS Independent
Classifier: License :: OSI Approved :: MIT License
Classifier: Programming Language :: Python
Classifier: Programming Language :: Python :: 3
Classifier: Programming Language :: Python :: 3.7
Provides-Extra: dev
Provides-Extra: test
Requires-Dist: invoke (==0.18.1)
Requires-Dist: python-dotenv (==0.10.2)
Requires-Dist: PyYAML (==5.1)
Requires-Dist: semver (==2.8.1)
Provides-Extra: dev
Requires-Dist: invoke (<=0.18.1,>=0.15); extra == 'dev'
Requires-Dist: pyyaml; extra == 'dev'
Requires-Dist: python-dotenv (>=0.5.1); extra == 'dev'
Requires-Dist: semver; extra == 'dev'
Provides-Extra: test
Requires-Dist: coverage; extra == 'test'
